lens/__init__.py
lens/bins.py
lens/dask_graph.py
lens/explorer.py
lens/formatting.py
lens/metrics.py
lens/plotting.py
lens/summarise.py
lens/tdigest_utils.py
lens/utils.py
lens/version.py
lens/widget.py
lens-0.4.5.dist-info/LICENSE.txt
lens-0.4.5.dist-info/METADATA
lens-0.4.5.dist-info/RECORD
lens-0.4.5.dist-info/WHEEL
lens-0.4.5.dist-info/top_level.txt
