Metadata-Version: 2.1
Name: lens
Version: 0.4.5
Summary: Summarise and explore Pandas DataFrames
Home-page: https://github.com/asidatascience/lens
Author: ASI Data Science
Author-email: engineering@asidatascience.com
License: Apache 2.0
Platform: UNKNOWN
Requires-Dist: dask[delayed,dataframe] (>=0.18.0)
Requires-Dist: ipywidgets (>=6.0.0)
Requires-Dist: matplotlib
Requires-Dist: numpy (>=1.11)
Requires-Dist: pandas
Requires-Dist: plotly (>=3.0.0)
Requires-Dist: scipy
Requires-Dist: tdigest (>=0.5.0)
Requires-Dist: seaborn
